Metadata-Version: 2.1
Name: tbreak
Version: 0.0.0
Summary: tbreak
Home-page: http://github.com/serwy/tbreak
Author: Roger D. Serwy
Author-email: roger.serwy@gmail.com
Classifier: Development Status :: 2 - Pre-Alpha
Classifier: Operating System :: OS Independent
Classifier: Programming Language :: Python :: 3
